cnl2feedcrawler/__init__.py
cnl2feedcrawler/run.py
cnl2feedcrawler/providers/__init__.py
cnl2feedcrawler/providers/version.py
cnl2feedcrawler/providers/http_requests/__init__.py
cnl2feedcrawler/providers/http_requests/request_handler.py
cnl2feedcrawler-3.0.0.dist-info/LICENSE
cnl2feedcrawler-3.0.0.dist-info/METADATA
cnl2feedcrawler-3.0.0.dist-info/WHEEL
cnl2feedcrawler-3.0.0.dist-info/entry_points.txt
cnl2feedcrawler-3.0.0.dist-info/top_level.txt
cnl2feedcrawler-3.0.0.dist-info/RECORD
