Metadata-Version: 2.1
Name: cnl2feedcrawler
Version: 3.0.0
Summary: Intercept, decrypt and forward CnL to FeedCrawler
Home-page: https://github.com/rix1337/ClickNLoad2FeedCrawler
Author: rix1337
Author-email: 
License: UNKNOWN
Platform: UNKNOWN
Classifier: Programming Language :: Python :: 3
Classifier: License :: OSI Approved :: GNU General Public License v3 (GPLv3)
Classifier: Operating System :: POSIX :: Linux
License-File: LICENSE
Requires-Dist: dukpy (==0.4.0)
Requires-Dist: pycryptodomex (==3.20.0)
